{"symbol": "ARNC", "name": "Arconic Corporation", "price": 29.99, "changesPercentage": 0.0334, "change": 0.01, "dayLow": 29.98, "dayHigh": 30.02, "yearHigh": 30.02, "yearLow": 16.33, "marketCap": 3009376540, "priceAvg50": 29.621, "priceAvg200": 25.90155, "exchange": "NYSE", "volume": 4356209, "avgVolume": 1209558, "open": 29.99, "previousClose": 29.98, "eps": -2.39, "pe": -12.548117154811715, "earningsAnnouncement": "2023-10-30T00:00:00.000+0000", "sharesOutstanding": 100346000, "timestamp": 1692302402}