[{"asset": "EQIX", "name": "Equinix Inc", "isin": "US29444U7000", "cusip": "29444U700", "sharesNumber": 390, "weightPercentage": 6.278, "marketValue": 353535, "updated": "2025-06-26 03:06:59"}, {"asset": "AMT", "name": "American Tower Corp", "isin": "US03027X1000", "cusip": "03027X100", "sharesNumber": 1549, "weightPercentage": 6.159, "marketValue": 346836.59, "updated": "2025-06-26 03:06:59"}, {"asset": "DLR", "name": "Digital Realty Trust Inc", "isin": "US2538681030", "cusip": "253868103", "sharesNumber": 1827, "weightPercentage": 5.764, "marketValue": 324584.82, "updated": "2025-06-26 03:06:59"}, {"asset": "PLD", "name": "ProLogis Inc", "isin": "US74340W1036", "cusip": "74340W103", "sharesNumber": 2961, "weightPercentage": 5.685, "marketValue": 320172.93, "updated": "2025-06-26 03:06:59"}, {"asset": "CCI", "name": "Crown Castle Corp", "isin": "US22822V1017", "cusip": "22822V101", "sharesNumber": 2644, "weightPercentage": 4.845, "marketValue": 272834.36, "updated": "2025-06-26 03:06:59"}, {"asset": "GMG.AX", "name": "Goodman Group", "isin": "AU000000GMG2", "cusip": "Q4229W132", "sharesNumber": 11871, "weightPercentage": 4.761, "marketValue": 268136.62, "updated": "2025-06-26 03:06:59"}, {"asset": "IRM", "name": "Iron Mountain Inc", "isin": "US46284V1017", "cusip": "46284V101", "sharesNumber": 2502, "weightPercentage": 4.676, "marketValue": 263335.5, "updated": "2025-06-26 03:06:59"}, {"asset": "SBAC", "name": "SBA Communications Corp", "isin": "US78410G1040", "cusip": "78410G104", "sharesNumber": 994, "weightPercentage": 4.176, "marketValue": 235180.4, "updated": "2025-06-26 03:06:59"}, {"asset": "CORZ", "name": "Core Scientific Inc", "isin": "US21874A1060", "cusip": "21874A106", "sharesNumber": 18136, "weightPercentage": 3.932, "marketValue": 221440.56, "updated": "2025-06-26 03:06:59"}, {"asset": "CLNX.MC", "name": "Cellnex Telecom Sau", "isin": "ES0105066007", "cusip": "", "sharesNumber": 5615, "weightPercentage": 3.886, "marketValue": 218844.61, "updated": "2025-06-26 03:06:59"}, {"asset": "IREN", "name": "Iris Energy Ltd", "isin": "AU0000185993", "cusip": "Q4982L109", "sharesNumber": 15156, "weightPercentage": 3.106, "marketValue": 174900.24, "updated": "2025-06-26 03:06:59"}, {"asset": "ASTS", "name": "Ast Spacemobile Inc", "isin": "US00217D1000", "cusip": "00217D100", "sharesNumber": 3233, "weightPercentage": 3.055, "marketValue": 172060.26, "updated": "2025-06-26 03:06:59"}, {"asset": "ARE", "name": "Alexandria Real Estate Equities", "isin": "US0152711091", "cusip": "015271109", "sharesNumber": 2203, "weightPercentage": 2.948, "marketValue": 166040.11, "updated": "2025-06-26 03:06:59"}, {"asset": "SGRO.L", "name": "Segro PLC", "isin": "GB00B5ZN1N88", "cusip": "G80277141", "sharesNumber": 16320, "weightPercentage": 2.753, "marketValue": 155034.03, "updated": "2025-06-26 03:06:59"}, {"asset": "PEAK", "name": "Healthpeak Properties Inc", "isin": "US42250P1030", "cusip": "42250P103", "sharesNumber": 8754, "weightPercentage": 2.719, "marketValue": 153107.46, "updated": "2025-06-26 03:06:59"}, {"asset": "INW.MI", "name": "INWIT - Infrastrutture Wireless Spa", "isin": "IT0005090300", "cusip": "", "sharesNumber": 11311, "weightPercentage": 2.422, "marketValue": 136392.95, "updated": "2025-06-26 03:06:59"}, {"asset": "APLD", "name": "Applied Digital Corp", "isin": "US0381692070", "cusip": "038169207", "sharesNumber": 12862, "weightPercentage": 2.357, "marketValue": 132735.84, "updated": "2025-06-26 03:06:59"}, {"asset": "LINE", "name": "Lineage Inc", "isin": "US53566V1061", "cusip": "53566V106", "sharesNumber": 2757, "weightPercentage": 2.266, "marketValue": 127621.53, "updated": "2025-06-26 03:06:59"}, {"asset": "EGP", "name": "EastGroup Properties Inc", "isin": "US2772761019", "cusip": "277276101", "sharesNumber": 659, "weightPercentage": 2.033, "marketValue": 114481.48, "updated": "2025-06-26 03:06:59"}, {"asset": "A17U.SI", "name": "Ascendas Real Estate Investment", "isin": "SG1M77906915", "cusip": "", "sharesNumber": 53908, "weightPercentage": 1.96, "marketValue": 110393.72, "updated": "2025-06-26 03:06:59"}, {"asset": "HUT", "name": "Hut 8 Corp", "isin": "US44812J1043", "cusip": "44812T102", "sharesNumber": 6098, "weightPercentage": 1.867, "marketValue": 105129.52, "updated": "2025-06-26 03:06:59"}, {"asset": "REXR", "name": "Rexford Industrial Realty Inc", "isin": "US76169C1009", "cusip": "76169C100", "sharesNumber": 2813, "weightPercentage": 1.856, "marketValue": 104531.08, "updated": "2025-06-26 03:06:59"}, {"asset": "WULF", "name": "Terawulf Inc", "isin": "US88080T1043", "cusip": "88080T104", "sharesNumber": 23358, "weightPercentage": 1.593, "marketValue": 89694.72, "updated": "2025-06-26 03:06:59"}, {"asset": "CIFR", "name": "Cipher Mining Inc", "isin": "US17253J1060", "cusip": "17253J106", "sharesNumber": 22037, "weightPercentage": 1.507, "marketValue": 84842.45, "updated": "2025-06-26 03:06:59"}, {"asset": "TRNO", "name": "Terreno Realty Corp", "isin": "US88146M1018", "cusip": "88146M101", "sharesNumber": 1265, "weightPercentage": 1.318, "marketValue": 74204.9, "updated": "2025-06-26 03:06:59"}, {"asset": "NXT.AX", "name": "Nextdc Ltd", "isin": "AU000000NXT8", "cusip": "Q6750Y106", "sharesNumber": 7844, "weightPercentage": 1.313, "marketValue": 73963.96, "updated": "2025-06-26 03:06:59"}, {"asset": "BBOX.L", "name": "Tritax Big Box REIT Plc", "isin": "GB00BG49KP99", "cusip": "G9101W101", "sharesNumber": 29805, "weightPercentage": 1.086, "marketValue": 61141.91, "updated": "2025-06-26 03:06:59"}, {"asset": "COLD", "name": "Americold Realty Trust", "isin": "US03064D1081", "cusip": "03064D108", "sharesNumber": 3466, "weightPercentage": 1.069, "marketValue": 60204.42, "updated": "2025-06-26 03:06:59"}, {"asset": "3283.T", "name": "Nippon Prologis REIT Inc", "isin": "JP3047550003", "cusip": "", "sharesNumber": 105, "weightPercentage": 1.049, "marketValue": 59056.83, "updated": "2025-06-26 03:06:59"}, {"asset": "MLT.SI", "name": "Mapletree Logistics Trust", "isin": "", "cusip": "", "sharesNumber": 61547, "weightPercentage": 0.974, "marketValue": 54840.52, "updated": "2025-06-26 03:06:59"}, {"asset": "3281.T", "name": "GLP J-Reit", "isin": "JP3047510007", "cusip": "", "sharesNumber": 60, "weightPercentage": 0.964, "marketValue": 54268.44, "updated": "2025-06-26 03:06:59"}, {"asset": "MINT.SI", "name": "Mapletree Industrial Trust", "isin": "", "cusip": "", "sharesNumber": 34890, "weightPercentage": 0.954, "marketValue": 53722.6, "updated": "2025-06-26 03:06:59"}, {"asset": "KDCREIT.SI", "name": "Keppel DC REIT", "isin": "", "cusip": "", "sharesNumber": 27463, "weightPercentage": 0.869, "marketValue": 48940.98, "updated": "2025-06-26 03:06:59"}, {"asset": "IRDM", "name": "Iridium Communications Inc", "isin": "US46269C1027", "cusip": "46269C102", "sharesNumber": 1353, "weightPercentage": 0.695, "marketValue": 39142.29, "updated": "2025-06-26 03:06:59"}, {"asset": "GSAT", "name": "Globalstar Inc", "isin": "US3789735079", "cusip": "378973507", "sharesNumber": 1559, "weightPercentage": 0.658, "marketValue": 37073.02, "updated": "2025-06-26 03:06:59"}, {"asset": "LXP", "name": "LXP Industrial Trust", "isin": "US5290431015", "cusip": "529043101", "sharesNumber": 3685, "weightPercentage": 0.573, "marketValue": 32243.75, "updated": "2025-06-26 03:06:59"}, {"asset": "SESG.PA", "name": "Ses", "isin": "LU0088087324", "cusip": "L8300G135", "sharesNumber": 4458, "weightPercentage": 0.538, "marketValue": 30270.4, "updated": "2025-06-26 03:06:59"}, {"asset": "FLT.SI", "name": "Frasers Logistics &amp; Industrial Trust", "isin": "", "cusip": "", "sharesNumber": 46137, "weightPercentage": 0.528, "marketValue": 29750.43, "updated": "2025-06-26 03:06:59"}, {"asset": "1686.HK", "name": "Sunevision Holdings", "isin": "KYG857001054", "cusip": "G85700105", "sharesNumber": 29984, "weightPercentage": 0.504, "marketValue": 28379.83, "updated": "2025-06-26 03:06:59"}, {"asset": "3471.T", "name": "Mitsui Fudosan Logistics Park", "isin": "JP3048300002", "cusip": "", "sharesNumber": 39, "weightPercentage": 0.503, "marketValue": 28348.94, "updated": "2025-06-26 03:06:59"}, {"asset": "BTBT", "name": "Bit Digital Inc", "isin": "KYG1144A1058", "cusip": "G1144A105", "sharesNumber": 9635, "weightPercentage": 0.417, "marketValue": 23509.4, "updated": "2025-06-26 03:06:59"}, {"asset": "DBRG", "name": "Digitalbridge Group Inc", "isin": "US25401T6038", "cusip": "25401T108", "sharesNumber": 2194, "weightPercentage": 0.403, "marketValue": 22685.96, "updated": "2025-06-26 03:06:59"}, {"asset": "8967.T", "name": "Japan Logistics Fund Inc", "isin": "JP3046230003", "cusip": "", "sharesNumber": 34, "weightPercentage": 0.393, "marketValue": 22130.25, "updated": "2025-06-26 03:06:59"}, {"asset": "VSAT", "name": "Viasat Inc", "isin": "US92552V1008", "cusip": "92552V100", "sharesNumber": 1653, "weightPercentage": 0.381, "marketValue": 21455.94, "updated": "2025-06-26 03:06:59"}, {"asset": "3466.T", "name": "LaSalle Logiport REIT", "isin": "JP3048180008", "cusip": "", "sharesNumber": 22, "weightPercentage": 0.375, "marketValue": 21144.93, "updated": "2025-06-26 03:06:59"}, {"asset": "GOGO", "name": "Gogo Inc", "isin": "US38046C1099", "cusip": "38046C109", "sharesNumber": 1395, "weightPercentage": 0.356, "marketValue": 20060.1, "updated": "2025-06-26 03:06:59"}, {"asset": "HTWS.L", "name": "Helios Towers Plc", "isin": "GB00BJVQC708", "cusip": "G4431S102", "sharesNumber": 12270, "weightPercentage": 0.355, "marketValue": 19989.44, "updated": "2025-06-26 03:06:59"}, {"asset": "EREIT.SI", "name": "Esr-Reit", "isin": "", "cusip": "", "sharesNumber": 9857, "weightPercentage": 0.331, "marketValue": 18644.47, "updated": "2025-06-26 03:06:59"}, {"asset": "3481.T", "name": "Mitsubishi Estate Logistics", "isin": "JP3048480002", "cusip": "", "sharesNumber": 18, "weightPercentage": 0.263, "marketValue": 14800.48, "updated": "2025-06-26 03:06:59"}, {"asset": " ", "name": "Communications Sales &amp; Leasing Inc.", "isin": "", "cusip": "", "sharesNumber": 3024, "weightPercentage": 0.227, "marketValue": 12761.28, "updated": "2025-06-26 03:06:59"}, {"asset": "3487.T", "name": "Cre Logistics Reit Inc", "isin": "JP3048680007", "cusip": "", "sharesNumber": 8, "weightPercentage": 0.151, "marketValue": 8507.17, "updated": "2025-06-26 03:06:59"}, {"asset": "DCREIT.SI", "name": "Digital Core Reit Management", "isin": "", "cusip": "", "sharesNumber": 16165, "weightPercentage": 0.148, "marketValue": 8324.98, "updated": "2025-06-26 03:06:59"}]