[{"symbol": "AVES", "assetClass": "Equity", "aum": 759720914, "avgVolume": 60878, "cusip": "025072372", "description": "Invests in a broad set of companies of all market capitalizations across emerging markets countries and is designed to increase expected returns* by focusing on firms trading at what we believe are lower valuations with higher profitability ratios.**Pursues the benefits associated with indexing (diversification, low turnover, transparency of exposures), but with the ability to add value by making investment decisions using information in current prices.Efficient portfolio management and trading process that is designed to enhance returns while seeking to reduce unnecessary risks and costs for investors.Built to fit seamlessly into an investor's asset allocation.", "domicile": "US", "etfCompany": "Avantis", "expenseRatio": 0.36, "inceptionDate": "2021-09-27", "isin": "US0250723725", "name": "Avantis Emerging Markets Value ETF", "nav": 54.58, "navCurrency": "USD", "sectorsList": [{"industry": "Basic Materials", "exposure": 11.64}, {"industry": "Communication Services", "exposure": 6.06}, {"industry": "Consumer Cyclical", "exposure": 13.2}, {"industry": "Consumer Defensive", "exposure": 4.39}, {"industry": "Energy", "exposure": 4.6}, {"industry": "Financial Services", "exposure": 28.4}, {"industry": "Healthcare", "exposure": 5.03}, {"industry": "Industrials", "exposure": 11.59}, {"industry": "Real Estate", "exposure": 2.77}, {"industry": "Technology", "exposure": 9.9}, {"industry": "Utilities", "exposure": 2.42}], "website": "https://www.avantisinvestors.com/avantis-investments/avantis-emerging-markets-value-etf", "holdingsCount": 1706}]