[{"symbol": "BBLU", "assetClass": "Equity", "aum": 190050637, "avgVolume": 99858, "cusip": "02072L714", "description": "The fund is an actively managed exchange-traded fund (\"ETF\") sub-advised by Bridgeway Capital Management, LLC (the \"Sub-Adviser\") that seeks to achieve its investment objective by investing primarily in blue-chip stocks, and through some income almost exclusively derived from dividends paid by companies held in the fund's portfolio.", "domicile": "US", "etfCompany": null, "expenseRatio": 0.15, "inceptionDate": "2022-10-17", "isin": "US02072L7148", "name": "Ea Bridgeway Blue Chip ETF", "nav": 11.75, "navCurrency": "USD", "sectorsList": [{"industry": "Basic Materials", "exposure": 0}, {"industry": "Communication Services", "exposure": 13.29}, {"industry": "Consumer Cyclical", "exposure": 9.88}, {"industry": "Consumer Defensive", "exposure": 9.49}, {"industry": "Energy", "exposure": 4.92}, {"industry": "Financial Services", "exposure": 18.08}, {"industry": "Healthcare", "exposure": 12.97}, {"industry": "Industrials", "exposure": 2.47}, {"industry": "Real Estate", "exposure": 0}, {"industry": "Technology", "exposure": 28.91}, {"industry": "Utilities", "exposure": 0}], "website": "", "holdingsCount": 0}]