[{"symbol": "CG1.PA", "assetClass": "Equity", "aum": 1634930186, "avgVolume": 11856, "cusip": "", "description": "AMUNDI ETF DAX UCITS ETF DR seeks to replicate as closely as possible the performance of the DAX Index, whether the trend is rising or falling. This ETF enables investors to benefit from an exposure to the 40 largest companies by market capitalization in the German market and the most traded ones in the Prime Standard market segment of the Frankfurt Stock Exchange, in a single transaction.", "domicile": "FR", "etfCompany": "Amundi", "expenseRatio": 0.1, "inceptionDate": "2008-09-16", "isin": "FR0010655712", "name": "Amundi ETF DAX UCITS ETF DR", "nav": 431.35, "navCurrency": "EUR", "sectorsList": [{"industry": "Basic Materials", "exposure": 4.86}, {"industry": "Communication Services", "exposure": 6.45}, {"industry": "Consumer Cyclical", "exposure": 8.42}, {"industry": "Consumer Defensive", "exposure": 1.24}, {"industry": "Energy", "exposure": 0}, {"industry": "Financial Services", "exposure": 20.95}, {"industry": "Healthcare", "exposure": 5.65}, {"industry": "Industrials", "exposure": 29.83}, {"industry": "Real Estate", "exposure": 1.19}, {"industry": "Technology", "exposure": 17.77}, {"industry": "Utilities", "exposure": 3.65}], "website": "https://www.amundietf.nl/en/professional/products/equity/amundi-etf-dax-ucits-etf-dr/fr0010655712", "holdingsCount": 43}]