[{"symbol": "DBJA", "assetClass": "Equity", "aum": 5894887, "avgVolume": 2454, "cusip": "45782C136", "description": "The fund will invest substantially all of its assets in a portfolio of FLexible EXchange\u00ae Options (FLEX Options) that reference both the SPDR\u00ae S&P 500\u00ae ETF Trust (S&P 500 ETF) and the Invesco QQQ TrustSM, Series 1. FLEX Options are exchange-traded options contracts with uniquely customizable terms. The fund is non-diversified.", "domicile": "US", "etfCompany": "Innovator", "expenseRatio": 0.79, "inceptionDate": "2021-01-04", "isin": "US45782C1365", "name": "Innovator Double Stacker 9 Buffer ETF - January", "nav": 29.48, "navCurrency": "USD", "sectorsList": [{"industry": "Basic Materials", "exposure": 1.52}, {"industry": "Cash & Others", "exposure": 1.4210854715202004e-14}, {"industry": "Communication Services", "exposure": 10.57}, {"industry": "Consumer Cyclical", "exposure": 11.95}, {"industry": "Consumer Defensive", "exposure": 6.28}, {"industry": "Energy", "exposure": 2.85}, {"industry": "Financial Services", "exposure": 8.86}, {"industry": "Healthcare", "exposure": 10.89}, {"industry": "Industrials", "exposure": 7.32}, {"industry": "Real Estate", "exposure": 1.84}, {"industry": "Technology", "exposure": 35.93}, {"industry": "Utilities", "exposure": 1.99}], "website": "https://www.innovatoretfs.com/etf/?ticker=DBJA", "holdingsCount": 1}]