[{"symbol": "EXAG.DE", "assetClass": "Commodities", "aum": 219387827, "avgVolume": 3553, "cusip": "", "description": "NA", "domicile": "IE", "etfCompany": "WisdomTree", "expenseRatio": 0.6, "inceptionDate": "2021-07-07", "isin": "IE00BDVPNV63", "name": "WisdomTree Enhanced Commodity ex-Agriculture UCITS ETF - EUR Hedged Acc", "nav": 11.81, "navCurrency": "EUR", "sectorsList": [{"industry": "Cash & Others", "exposure": 100}], "website": "https://www.wisdomtree.eu/en-gb/etfs/commodities/exag-wisdomtree-enhanced-commodity-ex-agriculture---ucits-etf---eur-hedged-acc", "holdingsCount": 15}]