[{"symbol": "EXHF.DE", "assetClass": "Fixed Income", "aum": 166452976, "avgVolume": 972, "cusip": "", "description": "The Fund seeks to track the performance of an index composed of Eurozone investment grade government bonds.", "domicile": "DE", "etfCompany": "IShares", "expenseRatio": 0.15, "inceptionDate": "2006-07-11", "isin": "DE000A0H0785", "name": "iShares Euro Government Bond Capped 15-105yr UCITS ETF DE", "nav": 110.69, "navCurrency": "EUR", "sectorsList": [{"industry": "Cash & Others", "exposure": 100.00374}], "website": "https://www.ishares.com/ch/professionals/en/products/251834/ishares-euro-government-bond-capped-15105yr-ucits-etf-de-fund", "holdingsCount": 25}]