[{"symbol": "IUMO.L", "assetClass": "Equity", "aum": 640497407, "avgVolume": 158565, "cusip": "", "description": "The Fund seeks to track the performance of an index composed of a sub-set of MSCI USA stocks that have been experiencing an upward price trend.", "domicile": "IE", "etfCompany": "IShares", "expenseRatio": 0.2, "inceptionDate": "2016-10-13", "isin": "IE00BD1F4N50", "name": "iShares Edge MSCI USA Momentum Factor UCITS ETF", "nav": 16.59, "navCurrency": "USD", "sectorsList": [{"industry": "Basic Materials", "exposure": 0.00526}, {"industry": "Communication Services", "exposure": 10.8}, {"industry": "Consumer Cyclical", "exposure": 6.29}, {"industry": "Consumer Defensive", "exposure": 14.12}, {"industry": "Energy", "exposure": 2.05}, {"industry": "Financial Services", "exposure": 25.47}, {"industry": "Healthcare", "exposure": 7.69}, {"industry": "Industrials", "exposure": 9.6}, {"industry": "Real Estate", "exposure": 1.33}, {"industry": "Technology", "exposure": 17.89}, {"industry": "Utilities", "exposure": 4.77}], "website": "https://www.ishares.com/uk/individual/en/products/285208/ishares-edge-msci-usa-momentum-factor-ucits-etf", "holdingsCount": 125}]