[{"symbol": "MDY", "assetClass": "Equity", "aum": 23273640000, "avgVolume": 1289885, "cusip": "78467Y107", "description": "The SPDR S&P MIDCAP 400 ETF Trust seeks to provide investment results that, before expenses, correspond generally to the price and yield performance of the S&P MidCap 400 Index (the \u201cIndex\u201d)", "domicile": "US", "etfCompany": "SPDR", "expenseRatio": 0.23, "inceptionDate": "1995-05-04", "isin": "US78467Y1073", "name": "SPDR S&P MIDCAP 400 ETF Trust", "nav": 587.85, "navCurrency": "USD", "sectorsList": [{"industry": "Basic Materials", "exposure": 3.84}, {"industry": "Communication Services", "exposure": 1.14}, {"industry": "Consumer Cyclical", "exposure": 13.32}, {"industry": "Consumer Defensive", "exposure": 5.38}, {"industry": "Energy", "exposure": 4}, {"industry": "Financial Services", "exposure": 17.12}, {"industry": "Healthcare", "exposure": 8.57}, {"industry": "Industrials", "exposure": 22.04}, {"industry": "Real Estate", "exposure": 7.46}, {"industry": "Technology", "exposure": 14.53}, {"industry": "Utilities", "exposure": 2.6}], "website": "https://www.ssga.com/us/en/institutional/etfs/spdr-sp-midcap-400-etf-trust-mdy", "holdingsCount": 401}]