[{"symbol": "PSY.TO", "assetClass": "Equity", "aum": null, "avgVolume": 13, "cusip": "46139T103", "description": "PSY seeks to generate income and capital growth over the long term by investing, directly or indirectly, primarily in equities from developed markets globally.", "domicile": "CA", "etfCompany": "Invesco", "expenseRatio": 0.83, "inceptionDate": "2015-05-06", "isin": "CA46139T1030", "name": "Invesco Global Shareholder Yield ETF CAD", "nav": 30.82, "navCurrency": "CAD", "sectorsList": [{"industry": "Basic Materials", "exposure": 7.75}, {"industry": "Communication Services", "exposure": 7.27}, {"industry": "Consumer Cyclical", "exposure": 9.72}, {"industry": "Consumer Defensive", "exposure": 6.58}, {"industry": "Energy", "exposure": 9.71}, {"industry": "Financial Services", "exposure": 19.1}, {"industry": "Healthcare", "exposure": 11.29}, {"industry": "Industrials", "exposure": 8.46}, {"industry": "Real Estate", "exposure": 1.96}, {"industry": "Technology", "exposure": 10.53}, {"industry": "Utilities", "exposure": 7.63}], "website": "https://www.invesco.com/us/financial-products/etfs/product-detail?audienceType=Advisor&ticker=PSY.TO", "holdingsCount": null}]