[{"symbol": "SDEU.L", "assetClass": "Fixed Income", "aum": 173073771, "avgVolume": 3163, "cusip": "", "description": "The Fund seeks to track the performance of an index composed of German government bonds.", "domicile": "IE", "etfCompany": "IShares", "expenseRatio": 0.2, "inceptionDate": "2012-05-08", "isin": "IE00B5V94313", "name": "iShares Germany Govt Bond UCITS ETF", "nav": 105, "navCurrency": "GBP", "sectorsList": [{"industry": "Cash & Others", "exposure": 100.00310999999999}], "website": "https://www.ishares.com/uk/individual/en/products/251744/ishares-germany-government-bond-ucits-etf", "holdingsCount": 64}]