[{"symbol": "SVXY", "assetClass": "Volatility", "aum": 262201534, "avgVolume": 1179932, "cusip": "74347W130", "description": "ProShares Short VIX Short-Term Futures ETF seeks daily investment results, before fees and expenses, that correspond to one-half the inverse (-0.5x) of the daily performance of the S&P 500 VIX Short-Term Futures Index.", "domicile": "US", "etfCompany": "ProShares", "expenseRatio": 0.95, "inceptionDate": "2011-10-03", "isin": "US74347W1302", "name": "ProShares - Short VIX Short-Term Futures ETF", "nav": 45.45, "navCurrency": "USD", "sectorsList": [{"industry": "Cash & Others", "exposure": 100}], "website": "https://www.proshares.com/our-etfs/strategic/svxy", "holdingsCount": 3}]