[{"symbol": "URTH", "assetClass": "Equity", "aum": 5364033392, "avgVolume": 392159, "cusip": "464286392", "description": "The iShares MSCI World ETF seeks to track the investment results of an index composed of developed market equities.", "domicile": "US", "etfCompany": "IShares", "expenseRatio": 0.24, "inceptionDate": "2012-01-10", "isin": "US4642863926", "name": "iShares MSCI World ETF", "nav": 173.59, "navCurrency": "USD", "sectorsList": [{"industry": "Basic Materials", "exposure": 3.04}, {"industry": "Communication Services", "exposure": 8.61}, {"industry": "Consumer Cyclical", "exposure": 10.11}, {"industry": "Consumer Defensive", "exposure": 5.87}, {"industry": "Energy", "exposure": 3.47}, {"industry": "Financial Services", "exposure": 16.48}, {"industry": "Healthcare", "exposure": 9.21}, {"industry": "Industrials", "exposure": 10.81}, {"industry": "Real Estate", "exposure": 2.01}, {"industry": "Technology", "exposure": 27.82}, {"industry": "Utilities", "exposure": 2.56}], "website": "https://www.ishares.com/us/products/239696/ishares-msci-world-etf", "holdingsCount": 1323}]