[{"symbol": "VGK", "assetClass": "Europe Stock", "aum": 33300000000, "avgVolume": 5554429, "cusip": "922042874", "description": "Seeks to track the performance of the FTSE Developed Europe All Cap Index, which measures the investment return of stocks issued by companies located in the major markets of Europe.Holds stocks of companies located in Austria, Belgium, Denmark, Finland, France, Germany, Greece, Ireland, Italy, the Netherlands, Norway, Portugal, Spain, Sweden, Switzerland, and the United Kingdom.Follows a passively managed, full-replication approach.", "domicile": "US", "etfCompany": "Vanguard", "expenseRatio": 0.06, "inceptionDate": "2005-03-04", "isin": "US9220428745", "name": "Vanguard FTSE Europe ETF", "nav": 77.3, "navCurrency": "USD", "sectorsList": [{"industry": "Basic Materials", "exposure": 5.2}, {"industry": "Communication Services", "exposure": 4.05}, {"industry": "Consumer Cyclical", "exposure": 8.33}, {"industry": "Consumer Defensive", "exposure": 9.31}, {"industry": "Energy", "exposure": 4.16}, {"industry": "Financial Services", "exposure": 22.23}, {"industry": "Healthcare", "exposure": 13.26}, {"industry": "Industrials", "exposure": 19.43}, {"industry": "Real Estate", "exposure": 1.88}, {"industry": "Technology", "exposure": 8.22}, {"industry": "Utilities", "exposure": 3.93}], "website": "https://investor.vanguard.com/investment-products/etfs/profile/vgk", "holdingsCount": 1247}]