[{"symbol": "WBIY", "assetClass": "Equity", "aum": 64800500, "avgVolume": 5663, "cusip": "00400R858", "description": "Under normal circumstances the fund will invest at least 80% of its total assets in the securities of the underlying index. The underlying index is designed to select securities from the Solactive US Broad Market Index that exhibit certain yield and fundamental value characteristics. The parent index includes large, mid- and small-cap securities listed in the U.S., including approximately the 3,000 largest U.S. companies that are selected and weighted according to free float market capitalization.", "domicile": "US", "etfCompany": null, "expenseRatio": 0.99, "inceptionDate": "2016-12-22", "isin": "US00400R8584", "name": "WBI Power Factor High Dividend ETF", "nav": 31.57, "navCurrency": "USD", "sectorsList": [{"industry": "Basic Materials", "exposure": 5.02}, {"industry": "Communication Services", "exposure": 7.15}, {"industry": "Consumer Cyclical", "exposure": 16.92}, {"industry": "Consumer Defensive", "exposure": 19.09}, {"industry": "Energy", "exposure": 8.47}, {"industry": "Financial Services", "exposure": 17.32}, {"industry": "Healthcare", "exposure": 6.96}, {"industry": "Industrials", "exposure": 7.9}, {"industry": "Real Estate", "exposure": 0}, {"industry": "Technology", "exposure": 0.43575}, {"industry": "Utilities", "exposure": 10.74}], "website": "", "holdingsCount": 51}]