[{"etfSymbol": "VYMI", "assetExposure": "HYDR", "sharesNumber": 41940310, "weightPercentage": 0, "marketValue": 5.36}, {"etfSymbol": "VIHAX", "assetExposure": "HYDR", "sharesNumber": 41940310, "weightPercentage": 0, "marketValue": 5.36}, {"etfSymbol": "VFWAX", "assetExposure": "HYDR", "sharesNumber": 217254634, "weightPercentage": 0, "marketValue": 27.78}, {"etfSymbol": "VEU", "assetExposure": "HYDR", "sharesNumber": 217254634, "weightPercentage": 0, "marketValue": 27.78}, {"etfSymbol": "DFAX", "assetExposure": "HYDR", "sharesNumber": 5044, "weightPercentage": 0, "marketValue": 0}, {"etfSymbol": "DFAE", "assetExposure": "HYDR", "sharesNumber": 2375, "weightPercentage": 0, "marketValue": 0}]